PokeCorky/_Init_.py
PokeCorky/__init__.py
PokeCorky/pokemon.csv
PokeCorky/random_pokemon.py
PokeCorky-1.0.2.dist-info/METADATA
PokeCorky-1.0.2.dist-info/WHEEL
PokeCorky-1.0.2.dist-info/top_level.txt
PokeCorky-1.0.2.dist-info/RECORD
